setup.py
pySyncplicity/__init__.py
pySyncplicity/pySyncplicity.py
pySyncplicity.egg-info/PKG-INFO
pySyncplicity.egg-info/SOURCES.txt
pySyncplicity.egg-info/dependency_links.txt
pySyncplicity.egg-info/requires.txt
pySyncplicity.egg-info/top_level.txt
pySyncplicity/urls/__init__.py
pysyncplicity/__init__.py
pysyncplicity/pySyncplicity.py