Metadata-Version: 1.1
Name: pySyncplicity
Version: 0.0.1
Summary: A python module to interact with EMC Syncplicity
Home-page: http://packages.python.org/pysyncplicity
Author: Matt Cowger
Author-email: matt@cowger.us
License: BSD
Keywords: syncplicity
Platform: UNKNOWN
Classifier: Development Status :: 3 - Alpha
Classifier: Topic :: Utilities
Classifier: License :: OSI Approved :: BSD License
Classifier: Programming Language :: Python :: 2.7
Classifier: Topic :: Internet
